<?xml version="1.0" encoding="UTF-8"?>
<iati-activities version="2.03">
 <iati-activity default-currency="USD" dstore:dataset="unops-dk" dstore:index="49" hierarchy="1" iati-activities:generated-datetime="2021-04-27T15:10:33.180" iati-activities:version="2.03" last-updated-datetime="2021-04-26T02:47:06.870+02:00" xml:lang="EN" xmlns:dstore="http://d-portal.org/xmlns/dstore" xmlns:iati-activities="http://d-portal.org/xmlns/iati-activities">
  <iati-identifier>41AAA-22609-001</iati-identifier>
  <reporting-org ref="41AAA" type="40">
   <narrative xml:lang="EN">United Nations Office for Project Services</narrative>
  </reporting-org>
  <title>
   <narrative xml:lang="EN">Support to COVID-19 Recovery of Micro &amp; Small Enterprise Sector of Sri Lanka</narrative>
  </title>
  <description type="1">
   <narrative xml:lang="EN">The COVID-19 crisis has hit micro and small enterprises particularly hard in Sri Lanka. Health and safety of those working in these often congested enterprises is paramount in light of COVID-19, as is the need to keep them and the workers they employ financially afloat. With a return to work scenario imminent, this project provides support to micro and small enterprises to operate in a COVID-19 safe environment while assisting them to access working capital through Government and/or private sector channels to restart their businesses. The strategy includes micro and small enterprises support programmes, deployment of micro and small enterprises surveys, COVID specific Occupational Safety and Health training and purposing, business continuity planning, entrepreneurship support, manager-worker dialogue and on-line delivery channels and training thereby enhancing sustainability and ensuring decent work. This dual strategy of Occupational Safety and Health precautionary measures and access to working capital will help mitigate the adverse health and socio-economic impact on vulnerable enterprises and hundreds of thousands of workers they employ, allowing Sri Lanka to recover faster.

UNOPS implements the project together with ILO.</narrative>
  </description>
  <participating-org ref="41AAA" role="4" type="40">
   <narrative xml:lang="EN">United Nations Office for Project Services</narrative>
  </participating-org>
  <participating-org ref="41AAA" role="2" type="40">
   <narrative xml:lang="EN">United Nations Office for Project Services</narrative>
  </participating-org>
  <activity-status code="2"></activity-status>
  <activity-date iso-date="2020-05-28" type="2"></activity-date>
  <contact-info>
   <organisation>
    <narrative xml:lang="EN">United Nations Office for Project Services</narrative>
   </organisation>
   <person-name>
    <narrative xml:lang="EN">Cillian Domhnall OCATHAIL</narrative>
   </person-name>
   <telephone>4535467600</telephone>
   <email>info@unops.org</email>
   <mailing-address>
    <narrative xml:lang="EN">UNOPS HQ, PO Box 2695, 2100 Copenhagen, Denmark</narrative>
   </mailing-address>
  </contact-info>
  <recipient-country code="DK" percentage="100">
   <narrative xml:lang="EN">Denmark</narrative>
  </recipient-country>
  <location>
   <name>
    <narrative xml:lang="EN">Sri Lanka</narrative>
   </name>
   <description>
    <narrative xml:lang="EN">Sri Lanka</narrative>
   </description>
   <point srsName="http://www.opengis.net/def/crs/EPSG/0/4326">
    <pos>7.873054 80.771797</pos>
   </point>
   <location-class code="4"></location-class>
  </location>
  <collaboration-type code="2"></collaboration-type>
  <default-flow-type code="20"></default-flow-type>
  <default-finance-type code="110"></default-finance-type>
  <default-aid-type code="C01" vocabulary="1"></default-aid-type>
  <default-tied-status code="5"></default-tied-status>
  <budget type="1">
   <period-start iso-date="2020-01-01"></period-start>
   <period-end iso-date="2023-12-31"></period-end>
   <value currency="USD" value-date="2020-05-28">348285</value>
  </budget>
  <transaction ref="22609-001_2020_2023">
   <transaction-type code="2"></transaction-type>
   <transaction-date iso-date="2020-01-01"></transaction-date>
   <value currency="USD" value-date="2020-01-01">348285</value>
   <description>
    <narrative xml:lang="EN">Total partner commitment</narrative>
   </description>
   <provider-org>
    <narrative xml:lang="EN">Other UNDP MDTF</narrative>
   </provider-org>
   <receiver-org ref="41AAA">
    <narrative xml:lang="EN">United Nations Office for Project Services</narrative>
   </receiver-org>
   <disbursement-channel code="2"></disbursement-channel>
  </transaction>
  <transaction ref="22609-001_202012">
   <transaction-type code="4"></transaction-type>
   <transaction-date iso-date="2020-12-01"></transaction-date>
   <value currency="USD" value-date="2020-12-01">282832</value>
   <description>
    <narrative xml:lang="EN">Expenditure for 2020</narrative>
   </description>
   <provider-org ref="41AAA">
    <narrative xml:lang="EN">United Nations Office for Project Services</narrative>
   </provider-org>
   <disbursement-channel code="2"></disbursement-channel>
  </transaction>
  <transaction ref="22609-001_202101">
   <transaction-type code="4"></transaction-type>
   <transaction-date iso-date="2021-01-01"></transaction-date>
   <value currency="USD" value-date="2021-01-01">24657</value>
   <description>
    <narrative xml:lang="EN">Expenditure for 2021-January</narrative>
   </description>
   <provider-org ref="41AAA">
    <narrative xml:lang="EN">United Nations Office for Project Services</narrative>
   </provider-org>
   <disbursement-channel code="2"></disbursement-channel>
  </transaction>
  <transaction ref="22609-001_202102">
   <transaction-type code="4"></transaction-type>
   <transaction-date iso-date="2021-02-01"></transaction-date>
   <value currency="USD" value-date="2021-02-01">20778</value>
   <description>
    <narrative xml:lang="EN">Expenditure for 2021-February</narrative>
   </description>
   <provider-org ref="41AAA">
    <narrative xml:lang="EN">United Nations Office for Project Services</narrative>
   </provider-org>
   <disbursement-channel code="2"></disbursement-channel>
  </transaction>
  <transaction ref="22609-001_202103">
   <transaction-type code="4"></transaction-type>
   <transaction-date iso-date="2021-03-01"></transaction-date>
   <value currency="USD" value-date="2021-03-01">7334</value>
   <description>
    <narrative xml:lang="EN">Expenditure for 2021-March</narrative>
   </description>
   <provider-org ref="41AAA">
    <narrative xml:lang="EN">United Nations Office for Project Services</narrative>
   </provider-org>
   <disbursement-channel code="2"></disbursement-channel>
  </transaction>
  <document-link format="TEXT/HTML" url="https://data.unops.org/index.htm#SegmentCode=ORG&amp;FocusCode=DATA_PROJECTS&amp;EntityCode=PROJECT_ID&amp;EntityValue=22609-001">
   <title>
    <narrative xml:lang="EN">Activity website</narrative>
   </title>
   <category code="A12"></category>
   <language code="EN"></language>
  </document-link>
  <conditions attached="0"></conditions>
 </iati-activity>
</iati-activities>
