<?xml version="1.0" encoding="UTF-8"?>
<iati-activities version="2.02">
 <iati-activity default-currency="USD" dstore:dataset="unitedstates-bi" dstore:index="41" hierarchy="1" humanitarian="0" iati-activities:generated-datetime="2020-11-28T02:05:18" iati-activities:version="2.02" last-updated-datetime="2020-11-28T02:05:18" xml:lang="EN" xmlns:dstore="http://d-portal.org/xmlns/dstore" xmlns:iati-activities="http://d-portal.org/xmlns/iati-activities" xmlns:usg="http://www.foreignassistance.gov" xmlns:xsd="http://www.w3.org/2001/XMLSchema" xmlns:xsi="http://www.w3.org/2001/XMLSchema-instance">
  <iati-identifier>US-GOV-13-BI-5168</iati-identifier>
  <reporting-org ref="US-USAGOV" type="10">
   <narrative xml:lang="EN">The federal government of the United States</narrative>
  </reporting-org>
  <title>
   <narrative xml:lang="EN">Burundi Partner Cooperative Agreement Year 3</narrative>
  </title>
  <description>
   <narrative xml:lang="EN">Cooperative agreement for USADF Burundi Partner Association pour le D&#xE9;veloppement Transformationnel des Communaut&#xE9;s (DTC) to carry out year 3 of their cooperative agreement. Funds disbursed to provide liquidity in light of unanticipated shocks impacting project activities and grantee enterprises due to the COVID-19 pandemic.. Cooperative agreement for USADF Burundi Partner Association pour le D&#xE9;veloppement Transformationnel des Communaut&#xE9;s (DTC) to carry out year 3 of their cooperative agreement.</narrative>
  </description>
  <participating-org ref="US-USAGOV" role="1" type="10">
   <narrative xml:lang="EN">The federal government of the United States</narrative>
  </participating-org>
  <participating-org ref="US-GOV-13" role="2" type="10">
   <narrative xml:lang="EN">African Development Foundation</narrative>
  </participating-org>
  <participating-org ref="US-GOV-13" role="3" type="10">
   <narrative xml:lang="EN">African Development Foundation</narrative>
  </participating-org>
  <participating-org role="4" type="15">
   <narrative xml:lang="EN">Association pour le D&#xE9;veloppement Transformationnel des Communaut&#xE9;s (DTC)</narrative>
  </participating-org>
  <other-identifier ref="US-GOV" type="B1">
   <owner-org ref="US-USAGOV">
    <narrative xml:lang="EN">The federal government of the United States</narrative>
   </owner-org>
  </other-identifier>
  <activity-status code="4"></activity-status>
  <activity-date iso-date="2020-02-27" type="1">
   <narrative xml:lang="EN">Using transaction date.</narrative>
  </activity-date>
  <activity-date iso-date="2020-02-27" type="2">
   <narrative xml:lang="EN">Using transaction date.</narrative>
  </activity-date>
  <activity-date iso-date="2020-10-31" type="3"></activity-date>
  <activity-date iso-date="2020-10-31" type="4"></activity-date>
  <contact-info type="1">
   <organisation>
    <narrative xml:lang="EN">African Development Foundation</narrative>
   </organisation>
   <person-name>
    <narrative xml:lang="EN">Performance Management</narrative>
   </person-name>
   <telephone>+1 202-233-8800</telephone>
   <email>info@usadf.gov</email>
   <website>http://www.usadf.gov</website>
   <mailing-address>
    <narrative xml:lang="EN">1400 I Street NW Suite 1000, Washington, DC 20005-2248</narrative>
   </mailing-address>
  </contact-info>
  <activity-scope code="4"></activity-scope>
  <recipient-country code="BI" percentage="100"></recipient-country>
  <location ref="BI">
   <location-reach code="1"></location-reach>
   <name>
    <narrative xml:lang="EN">Burundi</narrative>
   </name>
   <description>
    <narrative xml:lang="EN">More than a decade since the conclusion of ten years of civil war and five years of civil conflict, Burundi is one of the least developed and most fragile countries in the world, with alarming levels of hunger and malnutrition that have been exacerbated by the current political crisis that started in April 2015. An ongoing refugee crisis, with over 200,000 Burundians registered in neighboring countries, is separating people from their land during harvest time and refugee returns in the future will create an increasingly complex food security and land problem. The primary goals of U.S. assistance in Burundi are promoting peace, stability, and equitable economic growth while improving the health status and social conditions of the population, reducing the high rates of chronic malnutrition, mitigating the drivers of conflict, and enhancing democratic governance and human rights. Additionally, the United States will support the professionalization of Burundi&apos;s military, which helps maintain peace and security both at home and in the region.</narrative>
   </description>
   <exactness code="1"></exactness>
   <location-class code="4"></location-class>
  </location>
  <collaboration-type code="1"></collaboration-type>
  <default-flow-type code="10"></default-flow-type>
  <default-finance-type code="110"></default-finance-type>
  <default-aid-type code="C01" vocabulary="1"></default-aid-type>
  <default-tied-status code="5"></default-tied-status>
  <budget>
   <period-start iso-date="2019-10-01"></period-start>
   <period-end iso-date="2020-09-30"></period-end>
   <value currency="USD" value-date="2019-10-01">270000</value>
  </budget>
  <transaction humanitarian="0">
   <transaction-type code="3"></transaction-type>
   <transaction-date iso-date="2020-06-02"></transaction-date>
   <value currency="USD" value-date="2020-06-02">10000</value>
   <description>
    <narrative xml:lang="EN">Disbursement</narrative>
   </description>
   <sector code="99810" vocabulary="1">
    <narrative xml:lang="EN">Sectors not specified</narrative>
   </sector>
   <sector code="5000" vocabulary="99">
    <narrative xml:lang="EN">Economic Development - General</narrative>
   </sector>
   <usg:treasury-account>
    <usg:fiscal-funding-year begin="2020" end="2020"></usg:fiscal-funding-year>
    <usg:main-account code="0700">African Development Foundation, Funds Appropriated to the President</usg:main-account>
    <usg:regular-account code="11"></usg:regular-account>
   </usg:treasury-account>
  </transaction>
  <transaction humanitarian="0">
   <transaction-type code="2"></transaction-type>
   <transaction-date iso-date="2020-02-27"></transaction-date>
   <value currency="USD" value-date="2020-02-27">150000</value>
   <description>
    <narrative xml:lang="EN">Obligation</narrative>
   </description>
   <sector code="99810" vocabulary="1">
    <narrative xml:lang="EN">Sectors not specified</narrative>
   </sector>
   <sector code="5000" vocabulary="99">
    <narrative xml:lang="EN">Economic Development - General</narrative>
   </sector>
   <usg:treasury-account>
    <usg:fiscal-funding-year begin="2020" end="2020"></usg:fiscal-funding-year>
    <usg:main-account code="0700">African Development Foundation, Funds Appropriated to the President</usg:main-account>
    <usg:regular-account code="11"></usg:regular-account>
   </usg:treasury-account>
  </transaction>
  <transaction humanitarian="0">
   <transaction-type code="3"></transaction-type>
   <transaction-date iso-date="2020-06-02"></transaction-date>
   <value currency="USD" value-date="2020-06-02">10000</value>
   <description>
    <narrative xml:lang="EN">Disbursement</narrative>
   </description>
   <sector code="99810" vocabulary="1">
    <narrative xml:lang="EN">Sectors not specified</narrative>
   </sector>
   <sector code="5000" vocabulary="99">
    <narrative xml:lang="EN">Economic Development - General</narrative>
   </sector>
   <usg:treasury-account>
    <usg:fiscal-funding-year begin="2020" end="2020"></usg:fiscal-funding-year>
    <usg:main-account code="0700">African Development Foundation, Funds Appropriated to the President</usg:main-account>
    <usg:regular-account code="11"></usg:regular-account>
   </usg:treasury-account>
  </transaction>
  <transaction humanitarian="0">
   <transaction-type code="3"></transaction-type>
   <transaction-date iso-date="2020-06-02"></transaction-date>
   <value currency="USD" value-date="2020-06-02">10000</value>
   <description>
    <narrative xml:lang="EN">Disbursement</narrative>
   </description>
   <sector code="99810" vocabulary="1">
    <narrative xml:lang="EN">Sectors not specified</narrative>
   </sector>
   <sector code="5000" vocabulary="99">
    <narrative xml:lang="EN">Economic Development - General</narrative>
   </sector>
   <usg:treasury-account>
    <usg:fiscal-funding-year begin="2020" end="2020"></usg:fiscal-funding-year>
    <usg:main-account code="0700">African Development Foundation, Funds Appropriated to the President</usg:main-account>
    <usg:regular-account code="11"></usg:regular-account>
   </usg:treasury-account>
  </transaction>
  <transaction humanitarian="0">
   <transaction-type code="3"></transaction-type>
   <transaction-date iso-date="2020-06-02"></transaction-date>
   <value currency="USD" value-date="2020-06-02">10000</value>
   <description>
    <narrative xml:lang="EN">Disbursement</narrative>
   </description>
   <sector code="99810" vocabulary="1">
    <narrative xml:lang="EN">Sectors not specified</narrative>
   </sector>
   <sector code="5000" vocabulary="99">
    <narrative xml:lang="EN">Economic Development - General</narrative>
   </sector>
   <usg:treasury-account>
    <usg:fiscal-funding-year begin="2020" end="2020"></usg:fiscal-funding-year>
    <usg:main-account code="0700">African Development Foundation, Funds Appropriated to the President</usg:main-account>
    <usg:regular-account code="11"></usg:regular-account>
   </usg:treasury-account>
  </transaction>
  <transaction humanitarian="0">
   <transaction-type code="3"></transaction-type>
   <transaction-date iso-date="2020-05-11"></transaction-date>
   <value currency="USD" value-date="2020-05-11">51967</value>
   <description>
    <narrative xml:lang="EN">Disbursement</narrative>
   </description>
   <sector code="99810" vocabulary="1">
    <narrative xml:lang="EN">Sectors not specified</narrative>
   </sector>
   <sector code="5000" vocabulary="99">
    <narrative xml:lang="EN">Economic Development - General</narrative>
   </sector>
   <usg:treasury-account>
    <usg:fiscal-funding-year begin="2020" end="2020"></usg:fiscal-funding-year>
    <usg:main-account code="0700">African Development Foundation, Funds Appropriated to the President</usg:main-account>
    <usg:regular-account code="11"></usg:regular-account>
   </usg:treasury-account>
  </transaction>
  <transaction humanitarian="0">
   <transaction-type code="3"></transaction-type>
   <transaction-date iso-date="2020-06-02"></transaction-date>
   <value currency="USD" value-date="2020-06-02">10000</value>
   <description>
    <narrative xml:lang="EN">Disbursement</narrative>
   </description>
   <sector code="99810" vocabulary="1">
    <narrative xml:lang="EN">Sectors not specified</narrative>
   </sector>
   <sector code="5000" vocabulary="99">
    <narrative xml:lang="EN">Economic Development - General</narrative>
   </sector>
   <usg:treasury-account>
    <usg:fiscal-funding-year begin="2020" end="2020"></usg:fiscal-funding-year>
    <usg:main-account code="0700">African Development Foundation, Funds Appropriated to the President</usg:main-account>
    <usg:regular-account code="11"></usg:regular-account>
   </usg:treasury-account>
  </transaction>
  <transaction humanitarian="0">
   <transaction-type code="3"></transaction-type>
   <transaction-date iso-date="2020-06-02"></transaction-date>
   <value currency="USD" value-date="2020-06-02">10000</value>
   <description>
    <narrative xml:lang="EN">Disbursement</narrative>
   </description>
   <sector code="99810" vocabulary="1">
    <narrative xml:lang="EN">Sectors not specified</narrative>
   </sector>
   <sector code="5000" vocabulary="99">
    <narrative xml:lang="EN">Economic Development - General</narrative>
   </sector>
   <usg:treasury-account>
    <usg:fiscal-funding-year begin="2020" end="2020"></usg:fiscal-funding-year>
    <usg:main-account code="0700">African Development Foundation, Funds Appropriated to the President</usg:main-account>
    <usg:regular-account code="11"></usg:regular-account>
   </usg:treasury-account>
  </transaction>
  <transaction humanitarian="0">
   <transaction-type code="3"></transaction-type>
   <transaction-date iso-date="2020-04-08"></transaction-date>
   <value currency="USD" value-date="2020-04-08">26939</value>
   <description>
    <narrative xml:lang="EN">Disbursement</narrative>
   </description>
   <sector code="99810" vocabulary="1">
    <narrative xml:lang="EN">Sectors not specified</narrative>
   </sector>
   <sector code="5000" vocabulary="99">
    <narrative xml:lang="EN">Economic Development - General</narrative>
   </sector>
   <usg:treasury-account>
    <usg:fiscal-funding-year begin="2020" end="2020"></usg:fiscal-funding-year>
    <usg:main-account code="0700">African Development Foundation, Funds Appropriated to the President</usg:main-account>
    <usg:regular-account code="11"></usg:regular-account>
   </usg:treasury-account>
  </transaction>
  <conditions attached="0"></conditions>
  <usg:mechanism-signing-date iso-date="2020-02-27"></usg:mechanism-signing-date>
 </iati-activity>
</iati-activities>
