<?xml version="1.0" encoding="UTF-8"?>
<iati-activities version="2.02">
 <iati-activity dstore:dataset="maec-sl" dstore:index="75" hierarchy="1" iati-activities:version="2.02" xml:lang="EN" xmlns:dstore="http://d-portal.org/xmlns/dstore" xmlns:iati-activities="http://d-portal.org/xmlns/iati-activities" xmlns:xsi="http://www.w3.org/2001/XMLSchema-instance" xsi:noNamespaceSchemaLocation="iati-activities-schema.xsd">
  <iati-identifier>ES-DIR3-E04585801-009-086347</iati-identifier>
  <reporting-org ref="ES-DIR3-E04585801" type="10">
   <narrative xml:lang="EN">Ministry of Foreign Affairs and Cooperation, Spain</narrative>
  </reporting-org>
  <title>
   <narrative xml:lang="ES">Ajuda emerg&#xE8;ncia para apoti ak St, John Ctaholic Hospital de Mabesseneh-Lunsar, a Sierrra Leona, para hacer frente al brote de ebola</narrative>
  </title>
  <description>
   <narrative xml:lang="ES">&quot;T&#xED;tulo completo del proyecto: Ajuda emerg&#xE8;ncia para apoti ak St, John Ctaholic Hospital de Mabesseneh-Lunsar, a Sierrra Leona, para hacer frente al brote de ebola :: Completar el equipamiento de la sala de aislamiento de personas sospechosas. Sensibilizar, formar y entrenar a todo el personal Assegurar la capacidad de atenci&#xF3;n sanitaria en el resto de especialidades Coordinar esfuerzos con las autoridades del poa&#xED;s y otras organizaciones Informar y formar a las autoridades tradicionales y pol&#xED;ticas locales hacer prevenci&#xF3;n, charlas y difusi&#xF3;n radiof&#xF3;nica.&quot;</narrative>
  </description>
  <participating-org ref="AC-47" role="2" xml:lang="ES">
   <narrative xml:lang="EN">EELL CAT - Catalu&#xF1;a</narrative>
  </participating-org>
  <participating-org ref="AC-47" role="3" xml:lang="ES">
   <narrative xml:lang="EN">EELL CAT - Catalu&#xF1;a</narrative>
  </participating-org>
  <participating-org ref="AC-175" role="3" xml:lang="ES">
   <narrative xml:lang="EN">EELL CAT AYTO EL PRAT DE LLOBREGAT</narrative>
  </participating-org>
  <participating-org ref="AC-212" role="4" xml:lang="ES">
   <narrative xml:lang="EN">FCCD - Fons Catal&#xE0; de Cooperaci&#xF3; al Desenvolupament</narrative>
  </participating-org>
  <participating-org role="1" type="10" xml:lang="EN">
   <narrative xml:lang="EN">Spain</narrative>
  </participating-org>
  <other-identifier ref="009-086347-SLE" type="A1">
   <owner-org ref="ES-DIR3-E04585801">
    <narrative xml:lang="EN">Ministry of Foreign Affairs and Cooperation, Spain</narrative>
   </owner-org>
  </other-identifier>
  <activity-status code="3"></activity-status>
  <activity-date iso-date="2014-12-22" type="1"></activity-date>
  <activity-date iso-date="2016-06-22" type="3"></activity-date>
  <contact-info>
   <organisation>
    <narrative xml:lang="EN">SGCID (Secretar&#xED;a General de Cooperaci&#xF3;n Internacional para el Desarrollo)</narrative>
   </organisation>
   <email>aod.sgpolde@maec.es</email>
   <website>https://infoaod.maec.es/</website>
  </contact-info>
  <recipient-country code="SL" percentage="100"></recipient-country>
  <recipient-region code="289" percentage="100" vocabulary="1"></recipient-region>
  <sector code="12220" percentage="100" vocabulary="1"></sector>
  <policy-marker code="1" significance="1" vocabulary="1"></policy-marker>
  <policy-marker code="2" significance="0" vocabulary="1"></policy-marker>
  <policy-marker code="3" significance="0" vocabulary="1"></policy-marker>
  <policy-marker code="4" significance="0" vocabulary="1"></policy-marker>
  <policy-marker code="5" significance="0" vocabulary="1"></policy-marker>
  <policy-marker code="6" significance="0" vocabulary="1"></policy-marker>
  <policy-marker code="7" significance="0" vocabulary="1"></policy-marker>
  <policy-marker code="8" significance="0" vocabulary="1"></policy-marker>
  <policy-marker code="9" significance="1" vocabulary="1"></policy-marker>
  <collaboration-type code="1"></collaboration-type>
  <default-flow-type code="10"></default-flow-type>
  <default-finance-type code="110"></default-finance-type>
  <default-aid-type code="C01" vocabulary="1"></default-aid-type>
  <default-tied-status code="4"></default-tied-status>
  <budget>
   <period-start iso-date="2014-12-22"></period-start>
   <period-end iso-date="2014-12-31"></period-end>
   <value currency="EUR" value-date="2014-12-22">4430.4</value>
  </budget>
  <planned-disbursement>
   <period-start iso-date="2014-12-22"></period-start>
   <period-end iso-date="2014-12-31"></period-end>
   <value currency="EUR" value-date="2014-12-22">4430.4</value>
  </planned-disbursement>
  <transaction>
   <transaction-type code="2"></transaction-type>
   <transaction-date iso-date="2014-12-22"></transaction-date>
   <value currency="EUR" value-date="2014-12-22">7384</value>
   <sector code="12220" vocabulary="1"></sector>
  </transaction>
  <transaction>
   <transaction-type code="3"></transaction-type>
   <transaction-date iso-date="2014-12-31"></transaction-date>
   <value currency="EUR" value-date="2014-12-31">4430.4</value>
   <sector code="12220" vocabulary="1"></sector>
  </transaction>
 </iati-activity>
</iati-activities>
